MANIFEST.in
README.md
setup.py
volta/__init__.py
volta.egg-info/PKG-INFO
volta.egg-info/SOURCES.txt
volta.egg-info/dependency_links.txt
volta.egg-info/entry_points.txt
volta.egg-info/requires.txt
volta.egg-info/top_level.txt
volta/api/__init__.py
volta/api/cli.py
volta/api/common.py
volta/api/http.py
volta/api/manager.py
volta/api/webserver.py
volta/api/worker.py
volta/common/__init__.py
volta/common/interfaces.py
volta/common/util.py
volta/core/__init__.py
volta/core/core.py
volta/core/postloader.py
volta/core/config/__init__.py
volta/core/config/dynamic_options.py
volta/core/config/schema.yaml
volta/listeners/__init__.py
volta/listeners/console/__init__.py
volta/listeners/console/plugin.py
volta/listeners/sync/__init__.py
volta/listeners/sync/sync.py
volta/providers/__init__.py
volta/providers/boxes/__init__.py
volta/providers/boxes/box500hz.py
volta/providers/boxes/box_binary.py
volta/providers/phones/__init__.py
volta/providers/phones/android.py
volta/providers/phones/android_old.py
volta/providers/phones/iphone.py
volta/providers/phones/nexus4.py
volta/providers/phones/binary/__init__.py
volta/providers/phones/binary/lightning-new3.apk
volta/providers/phones/binary/lightning.apk