Metadata-Version: 1.1
Name: volta
Version: 0.6.7
Summary: yandex package for mobile energy consumption measurements
Home-page: https://github.com/yandex-load/volta
Author: Alexey Lavrenuke (load testing)
Author-email: direvius@yandex-team.ru
License: MPLv2
Platform: UNKNOWN
Classifier: Environment :: Web Environment
Classifier: Intended Audience :: End Users/Desktop
Classifier: Intended Audience :: Developers
Classifier: Intended Audience :: System Administrators
Classifier: License :: OSI Approved :: GNU Lesser General Public License v2 or later (LGPLv2+)
Classifier: Operating System :: POSIX
Classifier: Topic :: Software Development :: Quality Assurance
Classifier: Topic :: Software Development :: Testing
Classifier: Topic :: Software Development :: Testing :: Traffic Generation
Classifier: Programming Language :: Python :: 2
Classifier: Programming Language :: Python :: 3
